[
  {
    "platform": "Twitch",
    "title": "カジュアル→クリコンカスタム≪実況≫夕餉前配信",
    "streamer": "せらヴぃ",
    "url": "https://www.twitch.tv/celavi_ch",
    "thumbnail": "https://static-cdn.jtvnw.net/previews-ttv/live_user_celavi_ch-320x180.jpg",
    "viewers": 48,
    "started_at": "2026-02-18T07:55:51Z"
  },
  {
    "platform": "Twitch",
    "title": "【FF14】超クリコン研究会 Day69【Kaheo】",
    "streamer": "kaheoCh",
    "url": "https://www.twitch.tv/kaheoch",
    "thumbnail": "https://static-cdn.jtvnw.net/previews-ttv/live_user_kaheoch-320x180.jpg",
    "viewers": 21,
    "started_at": "2026-02-18T09:42:34Z"
  },
  {
    "platform": "Twitch",
    "title": "今日は何着てクリコン走る?【FF14】竜騎士クリコン in Gaia",
    "streamer": "ゆきはれ",
    "url": "https://www.twitch.tv/yukihale",
    "thumbnail": "https://static-cdn.jtvnw.net/previews-ttv/live_user_yukihale-320x180.jpg",
    "viewers": 4,
    "started_at": "2026-02-18T08:00:14Z"
  }
]